sp_repo_review/__init__.py
sp_repo_review/_version.py
sp_repo_review/_version.pyi
sp_repo_review/families.py
sp_repo_review/py.typed
sp_repo_review/_compat/__init__.py
sp_repo_review/_compat/tomllib.py
sp_repo_review/_compat/importlib/__init__.py
sp_repo_review/_compat/importlib/resources/__init__.py
sp_repo_review/_compat/importlib/resources/abc.py
sp_repo_review/checks/__init__.py
sp_repo_review/checks/general.py
sp_repo_review/checks/github.py
sp_repo_review/checks/mypy.py
sp_repo_review/checks/noxfile.py
sp_repo_review/checks/precommit.py
sp_repo_review/checks/pyproject.py
sp_repo_review/checks/readthedocs.py
sp_repo_review/checks/ruff.py
sp_repo_review/checks/setupcfg.py
sp_repo_review/ruff_checks/__init__.py
sp_repo_review/ruff_checks/__main__.py
sp_repo_review/ruff_checks/ignore.json
sp_repo_review/ruff_checks/linter.json
sp_repo_review/ruff_checks/select.json
sp_repo_review-2025.11.10.dist-info/METADATA
sp_repo_review-2025.11.10.dist-info/WHEEL
sp_repo_review-2025.11.10.dist-info/entry_points.txt
sp_repo_review-2025.11.10.dist-info/licenses/LICENSE
sp_repo_review-2025.11.10.dist-info/RECORD
