Metadata-Version: 2.4
Name: sp_repo_review
Version: 2025.11.10
Summary: Review repos for compliance to the Scientific-Python development guidelines
Project-URL: Guide, https://learn.scientific-python.org/development
Project-URL: Homepage, https://github.com/scientific-python/cookie
Project-URL: Preview, https://scientific-python-cookie.readthedocs.io
Project-URL: Source, https://github.com/scientific-python/cookie
Author-email: Henry Schreiner <henryfs@princeton.edu>
License-Expression: BSD-3-Clause
License-File: LICENSE
Classifier: Development Status :: 4 - Beta
Classifier: Environment :: Console
Classifier: Environment :: WebAssembly :: Emscripten
Classifier: Intended Audience :: Developers
Classifier: Intended Audience :: Science/Research
Classifier: Operating System :: OS Independent
Classifier: Programming Language :: Python
Classifier: Programming Language :: Python :: 3
Classifier: Programming Language :: Python :: 3.10
Classifier: Programming Language :: Python :: 3.11
Classifier: Programming Language :: Python :: 3.12
Classifier: Programming Language :: Python :: 3.13
Classifier: Programming Language :: Python :: 3.14
Classifier: Topic :: Scientific/Engineering
Classifier: Topic :: Software Development :: Libraries :: Python Modules
Classifier: Topic :: Software Development :: Quality Assurance
Classifier: Typing :: Typed
Requires-Python: >=3.10
Requires-Dist: pyyaml
Requires-Dist: repo-review
Requires-Dist: tomli; python_version < '3.11'
Provides-Extra: all
Requires-Dist: repo-review[cli]; extra == 'all'
Requires-Dist: validate-pyproject-schema-store[all]; extra == 'all'
Provides-Extra: cli
Requires-Dist: repo-review[cli]; extra == 'cli'
Provides-Extra: pyproject
Requires-Dist: validate-pyproject-schema-store[all]; extra == 'pyproject'
